Metadata-Version: 1.0
Name: minimap
Version: 0.1.0
Summary: "Generate minimaps of your code"
Home-page: https://github.com/Ivoah/minimap
Author: Noah Rosamilia
Author-email: ivoahivoah@gmail.com
License: MIT
Keywords: source,code,image,generate
Platform: UNKNOWN
